{
  "portalAccountID": "00000000-0000-0000-0000-000000000000",
  "partnerID": "000000018",
  "firstName": "Caroline",
  "initials": "",
  "surname": "JOLY",
  "salutationCode": "2",
  "jobTitle": "",
  "languageCode": "FRA",
  "addressType": "PERSON",
  "houseNo": "6 ",
  "street": "RUE DE LA CHAPELLE AU BE",
  "address": "6 RUE DE LA CHAPELLE AU BE",
  "address2": "",
  "address3": "",
  "city": "ST ANDRE LES VERGERS",
  "county": "",
  "countryRegionCode": "FRA",
  "postCode": "10120",
  "phoneNo": "",
  "phoneNoPrivate": "",
  "faxNoPrivate": "",
  "extension": "",
  "eMail": "buat.caroline@cegetel.net",
  "eMail2": "buat.caroline@cegetel.net",
  "companyNo": "000000018",
  "companyName": "",
  "hasPendingOrder": true,
  "hasPendingContactInfo": true,
  "hasPendingPaymentUpdate": true,
  "hasPendingLumSumPayment": true,
  "addressAddition": "Herrn Thomas Becker"
}