{
  "webReferenceID": 9991312,
  "status": 0,
  "onlinePartnerID": "12345",
  "onlineType": 0,
  "onlineFirstName": "Paul",
  "onlineMiddleName": "",
  "onlineSurname": "Moser",
  "onlineDialectName": "",
  "onlineSalutationCode": "",
  "onlineJobTitleCode": "",
  "onlineCompName": "",
  "onlineCompName2": "",
  "onlineAdressAdditionType": "",
  "onlineAddrAddFirstName": "",
  "onlineAddrAddSurname": "",
  "onlineAddrAddSalCode": "",
  "onlineAddrAddJobTitleCode": "",
  "onlineStreet": "",
  "onlineHouseNo": "",
  "onlineAdress2": "",
  "onlineAdress3": "",
  "onlineDepartment": "",
  "onlinePostCode": "",
  "onlineCity": "",
  "onlineCountryCode": "",
  "onlinePOBox": "",
  "onlinePOBoxPostCode": "",
  "onlineRegionID": 0,
  "onlineTerritoryCode": "",
  "onlinePOBoxCountryCode": "",
  "onlineEmailPrivate": "",
  "onlinePhonePrivate": "",
  "onlineMobilePhoneNo": "",
  "onlineFaxNo": "",
  "onlineLanguageCode": "",
  "onlinePrevDonated": 0,
  "onlineChildID": 0,
  "onlineChildCountryCode": "",
  "onlineChildGender": "",
  "onlineChildAge": 0,
  "onlineRegionCode": "",
  "onlineMotivationCode": "",
  "onlineAmount": 0.0,
  "onlineFrequency": 0,
  "onlineCollectionDate": "1753-01-01T00:00:00",
  "onlinePaymentMeth": "",
  "onlineBankBranchNo": "",
  "onlineBankAccNo": "",
  "onlineSWIFTCode": "",
  "onlineIBAN": "",
  "onlineCreditCardNo": 0,
  "onlineCrCardHolder": "",
  "onlineCrCardExMonth": "",
  "onlineCrCardSecNo": 0,
  "onlineMotivationText": "",
  "onlineCrCardExYear": "",
  "onlineSalutationDescr": "",
  "onlineRegionDescr": "",
  "onlineEmailBusiness": "",
  "onlinePhoneBusiness": "",
  "preferredPhoneNo": 0,
  "preferredEmail": 0,
  "onlineBankAccountHolder": "",
  "paidOnline": 0,
  "externalReferenceNumber": "",
  "portalAccountID": "00000000-0000-0000-0000-000000000000",
  "productCode": "",
  "incidentType": "EINMALSPENDEN",
  "comments": "",
  "onlineAddressType": "",
  "onlineEmail": "",
  "onlineSalutation": "",
  "onlineRegionPartner": "",
  "onlineAddrAddSal": "",
  "emailType": 0,
  "phoneType1": 0,
  "phoneType2": 0,
  "mobilePhoneType": 0,
  "faxType": 0,
  "onlineBirthDate": "1753-01-01T00:00:00",
  "onlineExtAddrNo": "",
  "onlinePaymentID": 0,
  "onlinePartnerBankAcc": "",
  "nationalBank": 0,
  "bankOrCreditCard": 0,
  "onlineCrCardStartMonth": "",
  "onlineCrCardStartYear": "",
  "onlineCrCardType": "",
  "onlinePOBoxCity": ""
}